hpy/universal.cpython-39-darwin.so
hpy/devel/abitag.py
hpy/devel/version.py
hpy/devel/__init__.py
hpy/devel/include/hpy.h
hpy/devel/include/hpy/autogen_hpyslot.h
hpy/devel/include/hpy/version.h
hpy/devel/include/hpy/hpytype.h
hpy/devel/include/hpy/hpyexports.h
hpy/devel/include/hpy/hpydef.h
hpy/devel/include/hpy/inline_helpers.h
hpy/devel/include/hpy/macros.h
hpy/devel/include/hpy/hpymodule.h
hpy/devel/include/hpy/autogen_hpyfunc_declare.h
hpy/devel/include/hpy/cpy_types.h
hpy/devel/include/hpy/hpyfunc.h
hpy/devel/include/hpy/forbid_python_h/Python.h
hpy/devel/include/hpy/universal/hpyfunc_trampolines.h
hpy/devel/include/hpy/universal/autogen_trampolines.h
hpy/devel/include/hpy/universal/misc_trampolines.h
hpy/devel/include/hpy/universal/autogen_ctx.h
hpy/devel/include/hpy/universal/autogen_hpyfunc_trampolines.h
hpy/devel/include/hpy/runtime/argparse.h
hpy/devel/include/hpy/runtime/ctx_type.h
hpy/devel/include/hpy/runtime/buildvalue.h
hpy/devel/include/hpy/runtime/ctx_funcs.h
hpy/devel/include/hpy/runtime/ctx_module.h
hpy/devel/include/hpy/runtime/structseq.h
hpy/devel/include/hpy/runtime/format.h
hpy/devel/include/hpy/runtime/helpers.h
hpy/devel/include/hpy/cpython/hpyfunc_trampolines.h
hpy/devel/include/hpy/cpython/misc.h
hpy/devel/include/hpy/cpython/autogen_api_impl.h
hpy/devel/include/hpy/cpython/autogen_ctx.h
hpy/devel/include/hpy/cpython/autogen_hpyfunc_trampolines.h
hpy/devel/lib/universal/libhpy-extra-universal.a
hpy/devel/lib/cpython/libhpy-ctx-cpython.a
hpy/devel/lib/hybrid/libhpy-extra-hybrid.a
hpy/devel/src/runtime/ctx_bytes.c
hpy/devel/src/runtime/ctx_tracker.c
hpy/devel/src/runtime/ctx_tuple.c
hpy/devel/src/runtime/ctx_module.c
hpy/devel/src/runtime/ctx_eval.c
hpy/devel/src/runtime/format.c
hpy/devel/src/runtime/ctx_capsule.c
hpy/devel/src/runtime/ctx_object.c
hpy/devel/src/runtime/ctx_listbuilder.c
hpy/devel/src/runtime/structseq.c
hpy/devel/src/runtime/ctx_tuplebuilder.c
hpy-0.9.0.dist-info/RECORD
hpy-0.9.0.dist-info/LICENSE
hpy-0.9.0.dist-info/AUTHORS
hpy-0.9.0.dist-info/WHEEL
hpy-0.9.0.dist-info/entry_points.txt
hpy-0.9.0.dist-info/top_level.txt
hpy-0.9.0.dist-info/METADATA
