Metadata-Version: 2.1
Name: hpy
Version: 0.9.0
Summary: A better C API for Python
Home-page: https://hpyproject.org
Author: The HPy team
Author-email: hpy-dev@python.org
License: MIT
Requires-Python: >=3.8
License-File: LICENSE
License-File: AUTHORS
Requires-Dist: setuptools>=64.0
Provides-Extra: dev
Requires-Dist: pytest; extra == "dev"
Requires-Dist: pytest-xdist; extra == "dev"
Requires-Dist: filelock; extra == "dev"
